<?xml version="1.0" encoding="UTF-8"?>
<site>
   <feature id="org.eclipse.sdk.patch" version="0.0.0">
      <category name="Early Access of Java 8 support"/>
   </feature>
   <feature id="org.eclipse.jdt.patch" version="0.0.0">
      <category name="Early Access of Java 8 support"/>
   </feature>
   <feature id="org.eclipse.jdt.patch.source" version="0.0.0">
      <category name="Early Access of Java 8 support"/>
   </feature>
   <feature id="org.eclipse.pde.patch" version="0.0.0">
      <category name="Early Access of Java 8 support"/>
   </feature>   
   <feature id="org.eclipse.pde.patch.source" version="0.0.0">
      <category name="Early Access of Java 8 support"/>
   </feature>
   <category-def name="Early Access of Java 8 support" label="Early Access of Java 8 support"/>
</site>
